
<ObjectSpec>
<SpecVersion>18_0_1-167910</SpecVersion>
<Object>
<ObjClsGuid>1db606f2-af09-4cf9-a3b5-b481519d28f6</ObjClsGuid>
<ObjCls>0</ObjCls>
<ObjId>1</ObjId>
<ObjName>empleado</ObjName>
<ObjDesc>empleado</ObjDesc>
<ObjPgmName>empleado</ObjPgmName>
<ObjClsName>Transaction</ObjClsName></Object>
<Result>genreq</Result>
<Warnings></Warnings>
<Errors></Errors>
<Generator>
<GenId>41</GenId>
<GenName>Default (.NET)</GenName></Generator>
<FormClass>HTML</FormClass>
<Parameters>
<Parameter>
<IO>in</IO>
<Variable>
<VarId>Mode</VarId>
<VarName>&amp;Mode</VarName></Variable></Parameter>
<Parameter>
<IO>in</IO>
<Variable>
<VarId>Empleadoid</VarId>
<VarName>&amp;empleadoId</VarName></Variable></Parameter></Parameters>
<Levels>
<Level>
<LevelType>Trn</LevelType>
<LevelNumber>1</LevelNumber>
<BaseTable>
<Table>
<TableId>1</TableId>
<TableName>empleado</TableName>
<Description>empleado</Description></Table></BaseTable>
<NavigationTree>
<Table>
<TableId>1</TableId>
<TableName>empleado</TableName>
<Description>empleado</Description>
<Updated>Yes</Updated>
<RecordsToRead>many</RecordsToRead>
<KeyAttributes>
<Attribute>
<AttriId>1</AttriId>
<AttriName>empleadoId</AttriName>
<Description>empleado Id</Description></Attribute></KeyAttributes>
<Tables></Tables></Table></NavigationTree>
<Formulas>
<VerticalFormulas></VerticalFormulas>
<AggSelFormulas></AggSelFormulas></Formulas>
<DynamicLoads></DynamicLoads>
<Rules></Rules>
<AfterAttributeRules></AfterAttributeRules>
<AfterConfirmRules></AfterConfirmRules>
<TablesToUpdate>
<TableToUpdate>
<Table>
<TableId>1</TableId>
<TableName>empleado</TableName>
<Description>empleado</Description></Table>
<TableAction>insert</TableAction>
<AttrisToUpdate>
<Attribute>
<AttriId>9</AttriId>
<AttriName>empleadoName</AttriName>
<Description>empleado Name</Description></Attribute>
<Attribute>
<AttriId>10</AttriId>
<AttriName>empleadoCI</AttriName>
<Description>empleado CI</Description></Attribute>
<Attribute>
<AttriId>11</AttriId>
<AttriName>empleadoEmail</AttriName>
<Description>empleado Email</Description></Attribute>
<Attribute>
<AttriId>12</AttriId>
<AttriName>empleadoPhone</AttriName>
<Description>empleado Phone</Description></Attribute></AttrisToUpdate></TableToUpdate>
<TableToUpdate>
<Table>
<TableId>1</TableId>
<TableName>empleado</TableName>
<Description>empleado</Description></Table>
<TableAction>update</TableAction>
<AttrisToUpdate>
<Attribute>
<AttriId>9</AttriId>
<AttriName>empleadoName</AttriName>
<Description>empleado Name</Description></Attribute>
<Attribute>
<AttriId>10</AttriId>
<AttriName>empleadoCI</AttriName>
<Description>empleado CI</Description></Attribute>
<Attribute>
<AttriId>11</AttriId>
<AttriName>empleadoEmail</AttriName>
<Description>empleado Email</Description></Attribute>
<Attribute>
<AttriId>12</AttriId>
<AttriName>empleadoPhone</AttriName>
<Description>empleado Phone</Description></Attribute></AttrisToUpdate></TableToUpdate>
<TableToUpdate>
<Table>
<TableId>1</TableId>
<TableName>empleado</TableName>
<Description>empleado</Description></Table>
<TableAction>delete</TableAction>
<AttrisToUpdate></AttrisToUpdate></TableToUpdate></TablesToUpdate>
<AfterInsertRules></AfterInsertRules>
<AfterUpdateRules></AfterUpdateRules>
<AfterDeleteRules></AfterDeleteRules>
<TablesToControlOnDelete>
<Table>
<TableId>2</TableId>
<TableName>sucursal</TableName>
<Description>sucursal</Description>
<RecordsToRead>one</RecordsToRead>
<KeyAttributes>
<Attribute>
<AttriId>4</AttriId>
<AttriName>sucursalEmpleadoAlternateId</AttriName>
<Description>sucursal Empleado Alternate Id</Description></Attribute></KeyAttributes></Table>
<Table>
<TableId>2</TableId>
<TableName>sucursal</TableName>
<Description>sucursal</Description>
<RecordsToRead>one</RecordsToRead>
<KeyAttributes>
<Attribute>
<AttriId>3</AttriId>
<AttriName>sucursalEmpleadoHeadlineId</AttriName>
<Description>sucursal Empleado Headline Id</Description></Attribute></KeyAttributes></Table></TablesToControlOnDelete>
<Levels></Levels>
<AfterTrnRules></AfterTrnRules>
<AfterLevelRules></AfterLevelRules></Level></Levels>
<Suggests></Suggests></ObjectSpec>